huace_aigc_auth_client/__init__.py
huace_aigc_auth_client/api_stats_collector.py
huace_aigc_auth_client/legacy_adapter.py
huace_aigc_auth_client/sdk.py
huace_aigc_auth_client/user_context.py
huace_aigc_auth_client/webhook.py
huace_aigc_auth_client/webhook_flask.py
huace_aigc_auth_client-1.1.22.dist-info/licenses/LICENSE
huace_aigc_auth_client-1.1.22.dist-info/METADATA
huace_aigc_auth_client-1.1.22.dist-info/WHEEL
huace_aigc_auth_client-1.1.22.dist-info/top_level.txt
huace_aigc_auth_client-1.1.22.dist-info/RECORD
