Metadata-Version: 2.4
Name: huace-aigc-auth-client
Version: 1.1.22
Summary: 华策AIGC Auth Client - 提供 Token 验证、用户信息获取、权限检查、旧系统接入等功能
Author-email: Huace <support@huace.com>
License: MIT
Project-URL: Homepage, https://github.com/huace/huace-aigc-auth-client
Project-URL: Repository, https://github.com/huace/huace-aigc-auth-client
Keywords: aigc,auth,huace,sdk,authentication
Classifier: Development Status :: 4 - Beta
Classifier: Intended Audience :: Developers
Classifier: License :: OSI Approved :: MIT License
Classifier: Programming Language :: Python :: 3
Classifier: Programming Language :: Python :: 3.7
Classifier: Programming Language :: Python :: 3.8
Classifier: Programming Language :: Python :: 3.9
Classifier: Programming Language :: Python :: 3.10
Classifier: Programming Language :: Python :: 3.11
Classifier: Programming Language :: Python :: 3.12
Requires-Python: >=3.7
License-File: LICENSE
Requires-Dist: requests>=2.20.0
Dynamic: license-file
